tuauth/__init__.py
tuauth/backend.py
django_tuauth-1.0.dist-info/LICENSE
django_tuauth-1.0.dist-info/METADATA
django_tuauth-1.0.dist-info/WHEEL
django_tuauth-1.0.dist-info/top_level.txt
django_tuauth-1.0.dist-info/RECORD
