Metadata-Version: 2.1
Name: django-tuauth
Version: 1.0
Summary: A simple way to use TU authentication in django application.
Home-page: https://gitlab.com/ei-dev/scitu/oauth2/django-tuauth/
Author: Taratep Sira-aksorn
Author-email: taratep.sira@sci.tu.ac.th
License: MIT License
Platform: UNKNOWN
Classifier: Environment :: Web Environment
Classifier: Framework :: Django
Classifier: Framework :: Django :: 1.11
Classifier: Framework :: Django :: 2.0
Classifier: Intended Audience :: Developers
Classifier: License :: OSI Approved :: MIT License
Classifier: Operating System :: OS Independent
Classifier: Programming Language :: Python
Classifier: Programming Language :: Python :: 3.5
Classifier: Programming Language :: Python :: 3.6
Classifier: Topic :: Internet :: WWW/HTTP
Classifier: Topic :: Internet :: WWW/HTTP :: Dynamic Content
